{"cameraMode":{"drawMode":0,"name":"Shaded","section":"Shading Mode"},"sceneLighting":true,"audioPlay":false,"sceneViewState":{"m_AlwaysRefresh":false,"showFog":true,"showSkybox":true,"showFlares":true,"showImageEffects":true,"showParticleSystems":true,"showVisualEffectGraphs":true,"m_FxEnabled":true},"in2DMode":false,"pivot":{"x":-7.708492279052734,"y":5.3288068771362309,"z":-10.183151245117188},"rotation":{"x":-0.07817099243402481,"y":0.6529130339622498,"z":-0.06802283972501755,"w":-0.750313401222229},"size":15.366669654846192,"orthographic":false}